LICENSE
MANIFEST.in
README.md
setup.cfg
setup.py
ddd/__init__.py
ddd/__version__.py
ddd/aggregate_root.py
ddd/domain_event.py
ddd/domain_event_handler.py
ddd/domain_events.py
ddd/entity.py
ddd/process_domain_events.py
ddd/value_object.py
py_ddd.egg-info/PKG-INFO
py_ddd.egg-info/SOURCES.txt
py_ddd.egg-info/dependency_links.txt
py_ddd.egg-info/requires.txt
py_ddd.egg-info/top_level.txt
requirements/base.txt
requirements/ci.txt
requirements/test.txt
requirements/tox.txt