Metadata-Version: 1.1
Name: py-ddd
Version: 0.8.0
Summary: Domain-Driven Design framework for Python
Home-page: https://github.com/pristupa/ddd
Author: Pavel V. Pristupa
Author-email: pristupa@gmail.com
License: MIT
Platform: UNKNOWN
Classifier: Intended Audience :: Developers
Classifier: License :: OSI Approved :: MIT License
Classifier: Development Status :: 3 - Alpha
Classifier: Operating System :: OS Independent
Classifier: Environment :: Web Environment
Classifier: Programming Language :: Python
Classifier: Programming Language :: Python :: 3.6
Classifier: Programming Language :: Python :: 3.7
Classifier: Topic :: Software Development :: Libraries :: Application Frameworks
